geant4_pybind.cpython-310-darwin.so
geant4_pybind-0.1.1.dist-info/RECORD
geant4_pybind-0.1.1.dist-info/WHEEL
geant4_pybind-0.1.1.dist-info/top_level.txt
geant4_pybind-0.1.1.dist-info/METADATA
geant4_pybind-0.1.1.dist-info/licenses/LICENSE-3RD-PARTY
geant4_pybind-0.1.1.dist-info/licenses/LICENSE
