Metadata-Version: 2.4
Name: geant4_pybind
Version: 0.1.1
Summary: Alternative python bindings for Geant4 via pybind11
Home-page: https://github.com/HaarigerHarald/geant4_pybind
Author: Benjamin H.
Author-email: haarigerharald@gmx.at
License: Public Domain
Requires-Python: >=3.7, <4
License-File: LICENSE
License-File: LICENSE-3RD-PARTY
Dynamic: author
Dynamic: author-email
Dynamic: description
Dynamic: description-content-type
Dynamic: home-page
Dynamic: license
Dynamic: license-file
Dynamic: requires-python
Dynamic: summary
